cyapi/__init__.py
cyapi/cyapi.py
cyapi/exclusions/carbon_black.json
cyapi/exclusions/cs_falcon.json
cyapi/exclusions/defender.json
cyapi/exclusions/mcafee.json
cyapi/exclusions/ms_scep.json
cyapi/exclusions/sccm.json
cyapi/exclusions/sep.json
cyapi/exclusions/sophos.json
cyapi/exclusions/tanium.json
cyapi/exclusions/trend.json
cyapi/mixins/_Detections.py
cyapi/mixins/_DeviceCommands.py
cyapi/mixins/_Devices.py
cyapi/mixins/_Exceptions.py
cyapi/mixins/_Focus_View.py
cyapi/mixins/_Global_List.py
cyapi/mixins/_InstaQueries.py
cyapi/mixins/_MTC_HealthCheck.py
cyapi/mixins/_MTC_PolicyTemplates.py
cyapi/mixins/_MTC_Reports.py
cyapi/mixins/_MTC_Tenants.py
cyapi/mixins/_MTC_Users.py
cyapi/mixins/_Memory_Protection.py
cyapi/mixins/_Optics_Policies.py
cyapi/mixins/_Packages.py
cyapi/mixins/_Policies.py
cyapi/mixins/_Rules.py
cyapi/mixins/_Rulesets.py
cyapi/mixins/_Threats.py
cyapi/mixins/_Users.py
cyapi/mixins/_Zones.py
cyapi/mixins/__init__.py
cyapi/reqs/create_policy.json
cyapi-1.0.20.dist-info/WHEEL
cyapi-1.0.20.dist-info/METADATA
cyapi-1.0.20.dist-info/RECORD
