Metadata-Version: 2.1
Name: cyapi
Version: 1.0.20
Summary: Python bindings for Cylance Console and MTC
Home-page: https://github.com/cylance/python-cyapi
License: MIT
Author: Shane Shellenbarger
Author-email: soggysec@gmail.com
Classifier: License :: OSI Approved :: MIT License
Classifier: Programming Language :: Python :: 2
Classifier: Programming Language :: Python :: 2.7
Classifier: Programming Language :: Python :: 3
Classifier: Programming Language :: Python :: 3.4
Classifier: Programming Language :: Python :: 3.5
Classifier: Programming Language :: Python :: 3.6
Classifier: Programming Language :: Python :: 3.7
Classifier: Programming Language :: Python :: 3.8
Requires-Dist: futures; python_version == "2.7"
Requires-Dist: pyjwt
Requires-Dist: python-dateutil
Requires-Dist: pytz
Requires-Dist: requests
Requires-Dist: tqdm
Project-URL: Repository, https://github.com/cylance/python-cyapi
